cjy_wfy10/__init__.py
cjy_wfy10/background.jpg
cjy_wfy10/crash.wav
cjy_wfy10/font.ttf
cjy_wfy10/kaiti.ttf
cjy_wfy10/main.py
cjy_wfy10/racecar.jpg
cjy_wfy10/racestart.wav
cjy_wfy10/tiantiande.wav
cjy_wfy10/photos/1.jpg
cjy_wfy10/photos/10.jpg
cjy_wfy10/photos/11.jpg
cjy_wfy10/photos/12.jpg
cjy_wfy10/photos/13.jpg
cjy_wfy10/photos/14.jpg
cjy_wfy10/photos/15.jpg
cjy_wfy10/photos/2.jpg
cjy_wfy10/photos/3.jpg
cjy_wfy10/photos/4.jpg
cjy_wfy10/photos/5.jpg
cjy_wfy10/photos/6.jpg
cjy_wfy10/photos/7.jpg
cjy_wfy10/photos/70.jpg
cjy_wfy10/photos/8.jpg
cjy_wfy10/photos/9.jpg
cjy_wfy10-0.0.1.dist-info/LICENSE
cjy_wfy10-0.0.1.dist-info/METADATA
cjy_wfy10-0.0.1.dist-info/WHEEL
cjy_wfy10-0.0.1.dist-info/top_level.txt
cjy_wfy10-0.0.1.dist-info/RECORD
